<?xml version="1.0" encoding="utf-8" ?><dwsync><file name=".DS_Store" server="ehub24.webhostinghub.com" local="3456796705" remote="318763443850180752" Dst="-1" /><file name="AGATHA FLYER.jpg" server="ehub24.webhostinghub.com" local="3456796574" remote="318763443850180752" Dst="-1" /><file name="ADVENT SATURDAY 12-7.pdf" server="ehub24.webhostinghub.com" local="3456796546" remote="318763443850180752" Dst="-1" /><file name="autumn flyer 13 copy.jpg" server="ehub24.webhostinghub.com" local="3456796574" remote="318763443850180752" Dst="-1" /><file name="autumn fest invite back.pdf" server="ehub24.webhostinghub.com" local="3456796590" remote="318763443850180752" Dst="-1" /><file name="autumn flyer 13.jpg" server="ehub24.webhostinghub.com" local="3456796574" remote="318763443850180752" Dst="-1" /><file name="BE FIT Series.pdf" server="ehub24.webhostinghub.com" local="3456796512" remote="318763443850180752" Dst="-1" /><file name="GRATITUDE.pdf" server="ehub24.webhostinghub.com" local="3456796539" remote="318763443850180752" Dst="-1" /><file name="HERBAL 11-24.pdf" server="ehub24.webhostinghub.com" local="3456796562" remote="318763443850180752" Dst="-1" /><file name="CENTER UPDATE JUL-DEC 2013 PDF.pdf" server="ehub24.webhostinghub.com" local="3456796585" remote="318763443850180752" Dst="-1" /><file name="JESSE TREE 12-14.pdf" server="ehub24.webhostinghub.com" local="3456796554" remote="318763443850180752" Dst="-1" /><file name="NATIVE AMERICAN.pdf" server="ehub24.webhostinghub.com" local="3456796562" remote="318763443850180752" Dst="-1" /><file name="PEACE DAY 9-22.pdf" server="ehub24.webhostinghub.com" local="3456796554" remote="318763443850180752" Dst="-1" /><file name="SABBATH.pdf" server="ehub24.webhostinghub.com" local="3456796554" remote="318763443850180752" Dst="-1" /><file name="PEACE DAY.pdf" server="ehub24.webhostinghub.com" local="3456796567" remote="318763443850180752" Dst="-1" /><file name="autumn fest front.pdf" server="ehub24.webhostinghub.com" local="3456796590" remote="318763443850180752" Dst="-1" /></dwsync>